mistral_ai_ocr/__init__.py
mistral_ai_ocr/__main__.py
mistral_ai_ocr-1.4.dist-info/METADATA
mistral_ai_ocr-1.4.dist-info/WHEEL
mistral_ai_ocr-1.4.dist-info/entry_points.txt
mistral_ai_ocr-1.4.dist-info/top_level.txt
mistral_ai_ocr-1.4.dist-info/RECORD
