Metadata-Version: 2.1
Name: mistral-ai-ocr
Version: 1.4
Home-page: https://github.com/jfhack/mistral-ai-ocr
Requires-Dist: mistralai
Requires-Dist: python-dotenv
